LICENSE
README.rst
setup.cfg
setup.py
simplicial/__init__.py
simplicial/base.py
simplicial/embedding.py
simplicial/eulerintegrator.py
simplicial/filtration.py
simplicial/generators.py
simplicial/rep.py
simplicial/simplicialcomplex.py
simplicial/triangularlattice.py
simplicial/types.py
simplicial.egg-info/PKG-INFO
simplicial.egg-info/SOURCES.txt
simplicial.egg-info/dependency_links.txt
simplicial.egg-info/not-zip-safe
simplicial.egg-info/requires.txt
simplicial.egg-info/top_level.txt
simplicial/drawing/__init__.py
simplicial/drawing/drawing.py
simplicial/file/__init__.py
simplicial/file/json_simplicial.py
test/test_compose.py
test/test_eulerintegrator.py
test/test_filtration.py
test/test_flag.py
test/test_generators.py
test/test_homology.py
test/test_json_simplicial.py
test/test_randomplanes.py
test/test_simplicialcomplex.py
test/test_triangularlattice.py
test/test_vr.py